stereomolgraph/__init__.py
stereomolgraph/coords.py
stereomolgraph/experimental.py
stereomolgraph/graph2rdmol.py
stereomolgraph/ipython.py
stereomolgraph/periodic_table.py
stereomolgraph/py.typed
stereomolgraph/rdmol2graph.py
stereomolgraph/stereodescriptors.py
stereomolgraph/xyz2graph.py
stereomolgraph/algorithms/bond_orders.py
stereomolgraph/algorithms/color_refine.py
stereomolgraph/algorithms/isomorphism.py
stereomolgraph/graphs/__init__.py
stereomolgraph/graphs/crg.py
stereomolgraph/graphs/mg.py
stereomolgraph/graphs/scrg.py
stereomolgraph/graphs/smg.py
stereomolgraph-0.0.0b16.dist-info/licenses/LICENSE
stereomolgraph-0.0.0b16.dist-info/METADATA
stereomolgraph-0.0.0b16.dist-info/WHEEL
stereomolgraph-0.0.0b16.dist-info/top_level.txt
stereomolgraph-0.0.0b16.dist-info/RECORD
