Metadata-Version: 2.4
Name: StereoMolGraph
Version: 0.0.0b16
Summary: A graph library for chiral molecules, reactions and transition states
Author-email: Maxim Papusha <maxim.papusha@ltt.rwth-aachen.de>, Florian Solbach <florian.solbach@ltt.rwth-aachen.de>
Maintainer-email: Maxim Papusha <maxim.papusha@ltt.rwth-aachen.de>
Project-URL: Documentation, https://stereomolgraph.readthedocs.io/
Project-URL: Repository, https://github.com/maxim-papusha/StereoMolGraph.git
Project-URL: PyPi, https://pypi.org/project/StereoMolGraph/
Project-URL: Zenodo, https://doi.org/10.5281/zenodo.16360310
Keywords: chemistry,reaction,graph,molecule,transition state
Classifier: Development Status :: 4 - Beta
Classifier: Intended Audience :: Science/Research
Classifier: License :: OSI Approved :: MIT License
Classifier: Operating System :: OS Independent
Classifier: Topic :: Scientific/Engineering
Classifier: Topic :: Scientific/Engineering :: Chemistry
Classifier: Topic :: Scientific/Engineering :: Bio-Informatics
Classifier: Programming Language :: Python :: 3
Classifier: Programming Language :: Python :: 3.10
Classifier: Programming Language :: Python :: 3.11
Classifier: Programming Language :: Python :: 3.12
Classifier: Programming Language :: Python :: 3.13
Requires-Python: >=3.10
License-File: LICENSE
Requires-Dist: numpy<3,>=1.20
Requires-Dist: rdkit
Dynamic: license-file
